MANIFEST.in
README.md
bashcomplete.py
setup.py
python_bashcomplete.egg-info/PKG-INFO
python_bashcomplete.egg-info/SOURCES.txt
python_bashcomplete.egg-info/dependency_links.txt
python_bashcomplete.egg-info/top_level.txt