Metadata-Version: 1.1
Name: python-bashcomplete
Version: 1.1-0
Summary: bashcomplete creation from python lists and dictionaries.
Home-page: http://www.github.com/joaquincasares/python-bashcomplete
Author: Joaquin Casares
Author-email: joaquin.casares AT gmail.com
License: UNKNOWN
Download-URL: https://github.com/joaquincasares/python-bashcomplete/zipball/master
Keywords: python bashcomplete bash complete generation generate convert converter
Platform: UNKNOWN
